open_rarity/__init__.py
open_rarity/data/__init__.py
open_rarity/data/test_collections.json
open_rarity/models/__init__.py
open_rarity/models/chain.py
open_rarity/models/collection.py
open_rarity/models/token.py
open_rarity/models/token_identifier.py
open_rarity/models/token_metadata.py
open_rarity/models/token_ranking_features.py
open_rarity/models/token_rarity.py
open_rarity/models/token_standard.py
open_rarity/models/utils/__init__.py
open_rarity/models/utils/attribute_utils.py
open_rarity/rarity_ranker.py
open_rarity/resolver/__init__.py
open_rarity/resolver/models/__init__.py
open_rarity/resolver/models/collection_with_metadata.py
open_rarity/resolver/models/token_with_rarity_data.py
open_rarity/resolver/opensea_api_helpers.py
open_rarity/resolver/rarity_providers/__init__.py
open_rarity/resolver/rarity_providers/external_rarity_provider.py
open_rarity/resolver/rarity_providers/rank_resolver.py
open_rarity/resolver/rarity_providers/rarity_sniffer.py
open_rarity/resolver/rarity_providers/rarity_sniper.py
open_rarity/resolver/rarity_providers/trait_sniper.py
open_rarity/resolver/testset_resolver.py
open_rarity/scoring/__init__.py
open_rarity/scoring/handlers/__init__.py
open_rarity/scoring/handlers/arithmetic_mean_scoring_handler.py
open_rarity/scoring/handlers/geometric_mean_scoring_handler.py
open_rarity/scoring/handlers/harmonic_mean_scoring_handler.py
open_rarity/scoring/handlers/information_content_scoring_handler.py
open_rarity/scoring/handlers/scoring_handlers.md
open_rarity/scoring/handlers/sum_scoring_handler.py
open_rarity/scoring/scorer.py
open_rarity/scoring/scoring_handler.py
open_rarity/scoring/token_feature_extractor.py
open_rarity/scoring/utils.py
open_rarity-0.7.5.dist-info/LICENSE
open_rarity-0.7.5.dist-info/METADATA
open_rarity-0.7.5.dist-info/WHEEL
open_rarity-0.7.5.dist-info/RECORD
