Metadata-Version: 2.1
Name: open-rarity
Version: 0.7.5
Summary: Open-Rarity library is an open standard that provides an easy, explanable and reproducible computation for NFT rarity
License: Apache-2.0
Author: Dan Meshkov
Author-email: daniil.meshkov@opensea.io
Requires-Python: >=3.10,<3.13
Classifier: Development Status :: 4 - Beta
Classifier: Intended Audience :: Developers
Classifier: License :: OSI Approved :: Apache Software License
Classifier: Natural Language :: English
Classifier: Programming Language :: Python
Classifier: Programming Language :: Python :: 3
Classifier: Programming Language :: Python :: 3.10
Classifier: Programming Language :: Python :: 3.11
Classifier: Topic :: Software Development :: Libraries
Classifier: Typing :: Typed
Requires-Dist: numpy (>=1.23.1)
Requires-Dist: pydantic (>=1.9.1,<2.3)
Requires-Dist: requests (>=2.28.1)
